odoo/addons/sale_margin_security/README.rst
odoo/addons/sale_margin_security/__init__.py
odoo/addons/sale_margin_security/__manifest__.py
odoo/addons/sale_margin_security/i18n/es.po
odoo/addons/sale_margin_security/i18n/it.po
odoo/addons/sale_margin_security/i18n/sale_margin_security.pot
odoo/addons/sale_margin_security/readme/CONFIGURE.rst
odoo/addons/sale_margin_security/readme/CONTRIBUTORS.rst
odoo/addons/sale_margin_security/readme/DESCRIPTION.rst
odoo/addons/sale_margin_security/readme/USAGE.rst
odoo/addons/sale_margin_security/report/__init__.py
odoo/addons/sale_margin_security/report/sale_report.py
odoo/addons/sale_margin_security/security/sale_margin_security_security.xml
odoo/addons/sale_margin_security/static/description/icon.png
odoo/addons/sale_margin_security/static/description/index.html
odoo/addons/sale_margin_security/views/sale_margin_security_view.xml
odoo14_addon_sale_margin_security-14.0.1.0.1.dev8.dist-info/METADATA
odoo14_addon_sale_margin_security-14.0.1.0.1.dev8.dist-info/WHEEL
odoo14_addon_sale_margin_security-14.0.1.0.1.dev8.dist-info/top_level.txt
odoo14_addon_sale_margin_security-14.0.1.0.1.dev8.dist-info/RECORD
